cybsuite/__init__.py
cybsuite/cli/__init__.py
cybsuite/cli/cyberdb/__init__.py
cybsuite/cli/cyberdb/__main__.py
cybsuite/cli/cyberdb/cmd_cleardb.py
cybsuite/cli/cyberdb/cmd_ingest.py
cybsuite/cli/cyberdb/cmd_makemigrations.py
cybsuite/cli/cyberdb/cmd_migrate.py
cybsuite/cli/cyberdb/cmd_report.py
cybsuite/cli/cyberdb/cmd_scan.py
cybsuite/cli/cyberdb/cmd_schema.py
cybsuite/cli/cyberdb/cmd_search.py
cybsuite/cli/cyberdb/cmd_stats.py
cybsuite/cli/cyberdb/cmdi_list.py
cybsuite/cli/cyberdb/main_cli.py
cybsuite/cli/cyberdb/utils_cmd.py
cybsuite/cli/review/__init__.py
cybsuite/cli/review/__main__.py
cybsuite/cli/review/cmd_add.py
cybsuite/cli/review/cmd_get_extract_script.py
cybsuite/cli/review/cmd_list.py
cybsuite/cli/review/cmd_review.py
cybsuite/cli/review/main_cli.py
cybsuite/cli/workspace/__init__.py
cybsuite/cli/workspace/__main__.py
cybsuite/cli/workspace/cmd_create.py
cybsuite/cli/workspace/cmd_delete.py
cybsuite/cli/workspace/cmd_info.py
cybsuite/cli/workspace/cmd_switch.py
cybsuite/cli/workspace/main_cli.py
cybsuite/consts.py
cybsuite/core/__init__.py
cybsuite/core/config.py
cybsuite/core/install.py
cybsuite/core/logger.py
cybsuite/core/printer.py
cybsuite/cyberdb/__init__.py
cybsuite/cyberdb/bases/__init__.py
cybsuite/cyberdb/bases/base_formatter.py
cybsuite/cyberdb/bases/base_ingestor.py
cybsuite/cyberdb/bases/base_passive_scanner.py
cybsuite/cyberdb/bases/base_reporter.py
cybsuite/cyberdb/config.py
cybsuite/cyberdb/consts.py
cybsuite/cyberdb/cyberdb_scan_manager.py
cybsuite/cyberdb/cyberdb_scanner.py
cybsuite/cyberdb/cybsmodels/__init__.py
cybsuite/cyberdb/cybsmodels/cyberdb.py
cybsuite/cyberdb/cybsmodels/migrations/0001_initial.py
cybsuite/cyberdb/cybsmodels/migrations/0002_run_control_latest_run.py
cybsuite/cyberdb/cybsmodels/migrations/0003_run_status.py
cybsuite/cyberdb/cybsmodels/migrations/0004_alter_control_severity.py
cybsuite/cyberdb/cybsmodels/migrations/0005_alter_control_confidence.py
cybsuite/cyberdb/cybsmodels/migrations/__init__.py
cybsuite-0.1.1.dist-info/LICENSE
cybsuite-0.1.1.dist-info/METADATA
cybsuite-0.1.1.dist-info/WHEEL
cybsuite-0.1.1.dist-info/entry_points.txt
cybsuite-0.1.1.dist-info/RECORD
