Metadata-Version: 2.3
Name: cybsuite
Version: 0.1.1
Summary: CybSuite
License: Apache-2.0
Author: Nazime LAKEHAL
Author-email: nazime.lkh@gmail.com
Requires-Python: >=3.10,<4.0
Classifier: License :: OSI Approved :: Apache Software License
Classifier: Programming Language :: Python :: 3
Classifier: Programming Language :: Python :: 3.10
Classifier: Programming Language :: Python :: 3.11
Classifier: Programming Language :: Python :: 3.12
Classifier: Programming Language :: Python :: 3.13
Requires-Dist: django (>=5.2.1,<6.0.0)
Requires-Dist: fastapi (>=0.115.12,<0.116.0)
Requires-Dist: jinja2 (>=3.1.6,<4.0.0)
Requires-Dist: koalak (==0.4.2)
Requires-Dist: psycopg2-binary (>=2.9.10,<3.0.0)
Requires-Dist: python-dateutil (>=2.9.0.post0,<3.0.0)
Requires-Dist: python-multipart (>=0.0.20,<0.0.21)
Requires-Dist: requests (>=2.32.3,<3.0.0)
Requires-Dist: rich (>=14.0.0,<15.0.0)
Requires-Dist: uvicorn (>=0.34.2,<0.35.0)
